[
  {
    "text": "So back in the 1900s, Imperial Britain hastily withdrew from this area and made a series of decisions that contributed to long term instability that persists to this day. Actually, wait, sorry, They did do that here, but I'm not talking about this one. OK, try again. Back in the 1900s, Imperial Britain hastily withdrew from this area and made a series of decisions that contributed to you know what? This still isn't the right one. It's so hard to keep track. I think it's just a little more wisdom. All right, so back to the 1900s. No, sorry, forgot about that one. One more. There we go. OK, so back in the 1900s, Imperial Britain hastily withdrew from Cyprus and made a series of decisions that contributed to long term instability that persists to this day. Most political instability is not neat, but there's a very small portion of the political instability in Cyprus that is neat. And hear me out here. That's because it created this airport and this airport is illegal. HI says you're allowed to do political instability if it causes cool aviation logistics. This is Northern Cyprus's Air con International Airport. If you peek at its destinations, you can tell it's got a tantalizing set of international destinations, including Turkey, Turkey, Turkey, Turkey, Turkey, Turkey, Turkey, Turkey, Turkey, Turkey, and even Turkey.",
    "start_time": "0:00:00.48",
    "end_time": "0:01:09.24",
    "video_id": "8798066a",
    "keywords": [
      "political instability",
      "northern cyprus",
      "military zone",
      "destinations",
      "borders"
    ],
    "source": "azure_video_indexer"
  },
  {
    "text": "It's located here just north of one of those borders that's so messed up that it's not actually technically accurate to even call it a border because nobody really ever agreed it was a border. This is just where two different groups of people who really wanted Cyprus stopped fighting and it's actually the closest equivalent of the world to the much more iconic Korean DMZ. The Cypress one is also run by the UN. It's also a non military zone flanked on two sides by much military and it's also supposed to be temporary but as of yet isn't. It's also low key a bummer because there's a bunch of stuff and things in it that people used to use like houses and farms in this beach town, but also an entirely unrelated airport. That's kind of cool because everyone left it in like 1 day and it still looks exactly like it did on that one day because the UN said no you're not allowed to go there. So anyways, borders kind of cooked. Also Britain's still down there for some reason. Shenanigans were clearly happier. Those shenanigans got started really, really early because Cyprus spent time under control by the Greeks and the Persians and.",
    "start_time": "0:01:09.24",
    "end_time": "0:02:00",
    "video_id": "8798066a",
    "keywords": [
      "political instability",
      "northern cyprus",
      "military zone",
      "destinations",
      "borders"
    ],
    "source": "azure_video_indexer"
  }
]